README.md
setup.py
src/vdk/plugin/gdp/execution_id/gdp_execution_id_configuration.py
src/vdk/plugin/gdp/execution_id/gdp_execution_id_plugin.py
src/vdk_gdp_execution_id.egg-info/PKG-INFO
src/vdk_gdp_execution_id.egg-info/SOURCES.txt
src/vdk_gdp_execution_id.egg-info/dependency_links.txt
src/vdk_gdp_execution_id.egg-info/entry_points.txt
src/vdk_gdp_execution_id.egg-info/requires.txt
src/vdk_gdp_execution_id.egg-info/top_level.txt