Metadata-Version: 2.1
Name: vdk-gdp-execution-id
Version: 0.0.1181636991
Summary: This Versatile Data Kit SDK plugin is a Generative Data Pack, that expands each ingested dataset with the execution ID detected during data job run.
Home-page: https://github.com/vmware/versatile-data-kit
Classifier: Development Status :: 4 - Beta
Classifier: License :: OSI Approved :: Apache Software License
Classifier: Programming Language :: Python :: 3.7
Classifier: Programming Language :: Python :: 3.8
Classifier: Programming Language :: Python :: 3.9
Classifier: Programming Language :: Python :: 3.10
Classifier: Programming Language :: Python :: 3.11
Requires-Dist: vdk-core
